langgraph/store/mongodb/__init__.py
langgraph/store/mongodb/base.py
langgraph/store/mongodb/utils.py
langgraph_store_mongodb-0.2.0.dist-info/METADATA
langgraph_store_mongodb-0.2.0.dist-info/WHEEL
langgraph_store_mongodb-0.2.0.dist-info/RECORD
