Metadata-Version: 2.4
Name: langgraph-store-mongodb
Version: 0.2.0
Summary: MongoDB implementation of the LangGraph long-term memory store.
Requires-Python: >=3.10
Requires-Dist: langchain-mongodb>=0.11.0
Requires-Dist: langgraph-checkpoint>=3.0.0
Requires-Dist: pymongo-search-utils>=0.2.1
